influxify/__init__.py
influxify/main.py
influxify-0.0.3.dist-info/LICENSE
influxify-0.0.3.dist-info/METADATA
influxify-0.0.3.dist-info/WHEEL
influxify-0.0.3.dist-info/top_level.txt
influxify-0.0.3.dist-info/RECORD
