Metadata-Version: 2.1
Name: influxify
Version: 0.0.3
Summary: A package that can be used to convert csv file to influxdb line protocol format.
Home-page: https://github.com/saniauzma/Influxify
Author-email: uzmasaajid@gmail.com
License: MIT License
Project-URL: Source Code, https://github.com/saniauzma/Influxify
Project-URL: Bug Tracker, https://github.com/saniauzma/Influxify/issues
Classifier: Programming Language :: Python :: 3
Classifier: License :: OSI Approved :: MIT License
Classifier: Operating System :: OS Independent
License-File: LICENSE
